setup.py
dsku/__init__.py
dsku/dsku.py
dsku.egg-info/PKG-INFO
dsku.egg-info/SOURCES.txt
dsku.egg-info/dependency_links.txt
dsku.egg-info/entry_points.txt
dsku.egg-info/not-zip-safe
dsku.egg-info/requires.txt
dsku.egg-info/top_level.txt