Metadata-Version: 1.0
Name: dsku
Version: 0.2
Summary: Show disk usage with colored bars
Home-page: http://github.com/MartijnBraam/dsku
Author: Martijn Braam
Author-email: martijn@brixit.nl
License: MIT
Platform: UNKNOWN
